my_package/__init__.py
my_package/hello.py
my_package4430-1.0.0.dist-info/METADATA
my_package4430-1.0.0.dist-info/WHEEL
my_package4430-1.0.0.dist-info/top_level.txt
my_package4430-1.0.0.dist-info/RECORD
